easy_init/__init__.py
easy_init/easy_init.py
easy_init/test.py
easy_init-1.0.0.dist-info/DESCRIPTION.rst
easy_init-1.0.0.dist-info/METADATA
easy_init-1.0.0.dist-info/RECORD
easy_init-1.0.0.dist-info/WHEEL
easy_init-1.0.0.dist-info/metadata.json
easy_init-1.0.0.dist-info/top_level.txt
